anbani/__init__.py
anbani/core/__init__.py
anbani/core/converter.py
anbani/data/ambigram_nc1_len10.csv
anbani/data/ambigram_nc5_len7.csv
anbani/data/georgian_contractions.csv
anbani/data/letters.js
anbani/data/wordlist.csv
anbani/nlp/__init__.py
anbani/nlp/contractions.py
anbani/nlp/georgianisation.py
anbani/nlp/preprocessing.py
anbani/nlp/utils.py
anbani-0.9.5.dist-info/LICENSE
anbani-0.9.5.dist-info/METADATA
anbani-0.9.5.dist-info/WHEEL
anbani-0.9.5.dist-info/top_level.txt
anbani-0.9.5.dist-info/RECORD
