Metadata-Version: 2.1
Name: anbani
Version: 0.9.5
Summary: Georgian alphabet and language utilities for Natural Language Processing, script conversion and more.
Home-page: https://github.com/anbani/anbani.py
Author: George Gach
Author-email: georgegach@outlook.com
License: GPL
Platform: UNKNOWN
Classifier: Programming Language :: Python :: 3
Classifier: License :: OSI Approved :: GNU General Public License v3 (GPLv3)
Classifier: Operating System :: OS Independent
License-File: LICENSE
Requires-Dist: pymupdf
Requires-Dist: hjson
Requires-Dist: numpy
Requires-Dist: pandas
Requires-Dist: tqdm
